SDS/Api.py
SDS/Cache.py
SDS/Repository.py
SDS/Request.py
SDS/Token.py
SDS/__init__.py
SDS/main.py
SDS/Dataset/AuxData.py
SDS/Dataset/AuxStationData.py
SDS/Dataset/DeviceData.py
SDS/Dataset/ObjectData.py
SDS/Dataset/RuleData.py
SDS/Dataset/UserData.py
SDS/Dataset/WeatherData.py
SDS/Dataset/WorkflowsData.py
SDS/Dataset/__init__.py
SDS/Library/Pipeline.py
SDS/Library/__init__.py
SDS/OldApi/OldApi.py
SDS/OldApi/__init__.py
SDS/OldApi/Repository/Authenticate.py
SDS/OldApi/Repository/Object.py
SDS/OldApi/Repository/__init__.py
SDS/RepositoryApi/__init__.py
SDS/RepositoryApi/DataApi/Data.py
SDS/RepositoryApi/DataApi/__init__.py
SDS/RepositoryApi/ExeApi/ProcessExe.py
SDS/RepositoryApi/ExeApi/RuleExe.py
SDS/RepositoryApi/ExeApi/WorkflowsExe.py
SDS/RepositoryApi/ExeApi/__init__.py
SDS/RepositoryApi/OldApi/Authenticate.py
SDS/RepositoryApi/OldApi/AuxStation.py
SDS/RepositoryApi/OldApi/Object.py
SDS/RepositoryApi/OldApi/__init__.py
SDS/RepositoryApi/RuleApi/Rule.py
SDS/RepositoryApi/RuleApi/__init__.py
SDS/RepositoryApi/WeatherApi/Weather.py
SDS/RepositoryApi/WeatherApi/__init__.py
SDS/RepositoryApi/WorkflowApi/Workflows.py
SDS/RepositoryApi/WorkflowApi/__init__.py
sdsRayanArvin/Api.py
sdsRayanArvin/Cache.py
sdsRayanArvin/Repository.py
sdsRayanArvin/Request.py
sdsRayanArvin/Token.py
sdsRayanArvin/__init__.py
sdsRayanArvin/main.py
sdsRayanArvin/Dataset/AlertRuleData.py
sdsRayanArvin/Dataset/AuxStationData.py
sdsRayanArvin/Dataset/DeviceData.py
sdsRayanArvin/Dataset/ObjectData.py
sdsRayanArvin/Dataset/RuleData.py
sdsRayanArvin/Dataset/UserData.py
sdsRayanArvin/Dataset/WeatherData.py
sdsRayanArvin/Dataset/WorkflowsData.py
sdsRayanArvin/Dataset/__init__.py
sdsRayanArvin/Library/LastData.py
sdsRayanArvin/Library/Mqtt.py
sdsRayanArvin/Library/Pipeline.py
sdsRayanArvin/Library/__init__.py
sdsRayanArvin/RepositoryApi/__init__.py
sdsRayanArvin/RepositoryApi/DataApi/Data.py
sdsRayanArvin/RepositoryApi/DataApi/__init__.py
sdsRayanArvin/RepositoryApi/ExeApi/RuleExe.py
sdsRayanArvin-0.147.dist-info/METADATA
sdsRayanArvin-0.147.dist-info/WHEEL
sdsRayanArvin-0.147.dist-info/top_level.txt
sdsRayanArvin-0.147.dist-info/RECORD
