Metadata-Version: 2.1
Name: sdsRayanArvin
Version: 0.147
Summary: System data server
Home-page: https://hamgit.ir/v.heidary13/sds
Author: vahid heydari
License: UNKNOWN
Platform: UNKNOWN
